SDGraph/__init__.py
SDGraph/dependency_analysis.py
SDGraph/dependency_graph.py
SDGraph-0.0.5.data/scripts/SDGraph
SDGraph-0.0.5.dist-info/LICENSE
SDGraph-0.0.5.dist-info/METADATA
SDGraph-0.0.5.dist-info/WHEEL
SDGraph-0.0.5.dist-info/top_level.txt
SDGraph-0.0.5.dist-info/RECORD
