Metadata-Version: 2.1
Name: SDGraph
Version: 0.0.5
Summary: A simple jedi based python3 dependency analysis tool
Home-page: https://github.com/jam-world/py3_dependency_graph
Author: Cha Chen
Author-email: chencha92111@gmail.com
License: UNKNOWN
Platform: UNKNOWN
Classifier: Programming Language :: Python :: 3
Classifier: License :: OSI Approved :: MIT License
Classifier: Operating System :: OS Independent
Requires-Dist: GitPython
Requires-Dist: jedi
Requires-Dist: networkx
Requires-Dist: pygraphviz
